bt_proximity/__init__.py
bt_proximity/bt_rssi.py
bt_proximity-0.2.1.dist-info/LICENSE
bt_proximity-0.2.1.dist-info/METADATA
bt_proximity-0.2.1.dist-info/WHEEL
bt_proximity-0.2.1.dist-info/top_level.txt
bt_proximity-0.2.1.dist-info/RECORD
